countriesdb_validator-1.0.1.dist-info/licenses/LICENSE
validator/__init__.py
validator/types.py
validator/validator.py
countriesdb_validator-1.0.1.dist-info/METADATA
countriesdb_validator-1.0.1.dist-info/WHEEL
countriesdb_validator-1.0.1.dist-info/top_level.txt
countriesdb_validator-1.0.1.dist-info/RECORD
