Metadata-Version: 2.4
Name: countriesdb-validator
Version: 1.0.1
Summary: Backend validation package for CountriesDB - server-side validation for country and subdivision codes
Author-email: NAYEE LLC <contact@nayee.net>
License-Expression: LicenseRef-Proprietary
Project-URL: Homepage, https://countriesdb.com
Project-URL: Documentation, https://countriesdb.com/docs/backend-api
Project-URL: Examples, https://github.com/countriesdb/examples
Keywords: countries,subdivisions,validation,backend,server-side,countriesdb,iso-3166,iso-3166-1,iso-3166-2,country-codes,subdivision-codes,state-codes,province-codes,country-validation,subdivision-validation,address-validation,location-validation,geography,api-client,rest-api,python,django,flask,fastapi
Classifier: Development Status :: 5 - Production/Stable
Classifier: Intended Audience :: Developers
Classifier: Topic :: Software Development :: Libraries :: Python Modules
Classifier: Topic :: Internet :: WWW/HTTP :: Dynamic Content
Classifier: Topic :: Software Development :: Libraries
Classifier: Operating System :: OS Independent
Classifier: Programming Language :: Python :: 3
Classifier: Programming Language :: Python :: 3.8
Classifier: Programming Language :: Python :: 3.9
Classifier: Programming Language :: Python :: 3.10
Classifier: Programming Language :: Python :: 3.11
Classifier: Programming Language :: Python :: 3.12
Requires-Python: >=3.8
License-File: LICENSE
Requires-Dist: requests>=2.25.0
Dynamic: license-file
